guessing_machine/__init__.py
guessing_machine-0.0.2.dist-info/LICENSE
guessing_machine-0.0.2.dist-info/METADATA
guessing_machine-0.0.2.dist-info/WHEEL
guessing_machine-0.0.2.dist-info/top_level.txt
guessing_machine-0.0.2.dist-info/RECORD
